{
  "date": "2026-06-04",
  "market": "tw",
  "platform": "android",
  "chartType": "topfree",
  "chartName": "免費下載排行",
  "count": 100,
  "fetchedAt": "2026-06-04T13:02:44.547Z",
  "data": [
    {
      "rank": 1,
      "appId": "com.highbrow.games.dvo",
      "name": "Dragon Village 3",
      "developer": "highbrow",
      "icon": "https://play-lh.googleusercontent.com/xkwb3p2V6SkaxRq3uC_NM3n_tkw_UOcfe6uw75plux3o-e_XiY5Ixis8HTfjjix0U14HMqIbVNICs8IoVRFs",
      "score": 4.6153846,
      "ratings": 0,
      "category": "GAME",
      "url": "https://play.google.com/store/apps/details?id=com.highbrow.games.dvo",
      "price": 0,
      "free": true,
      "platform": "android",
      "summary": "龍養成、收集、即時對戰PVP的極致！可愛點陣龍打造專屬村莊。",
      "updated": "2026-06-02",
      "released": "2026-05-22",
      "contentRating": "適合 10 歲以上"
    },
    {
      "rank": 2,
      "appId": "com.ccstop.gp",
      "name": "車車屍搭普",
      "developer": "Higgs Technology Co., Limited",
      "icon": "https://play-lh.googleusercontent.com/w0ZKx2Dg_ssF6Yqn_I7gKBsdpDFkz66IZ24KIxaYRei7LS5eS31x8wqDA94NP7wYwUByqFVD3ri7Fk2h_bl_cQ",
      "score": 4.697479,
      "ratings": 0,
      "category": "GAME",
      "url": "https://play.google.com/store/apps/details?id=com.ccstop.gp",
      "price": 0,
      "free": true,
      "platform": "android",
      "summary": "報告！2026首款爽快飆車割草手遊來了！ 拒絕站樁慢打，載具就是武器，開車就是攻擊！ 現在預約送史詩載具「麻吉車車」、限定時裝「狂野道長」、武器「壓力粉碎機」！",
      "updated": "2026-06-03",
      "released": "",
      "contentRating": "適合青少年"
    },
    {
      "rank": 3,
      "appId": "com.nianticlabs.pikmin",
      "name": "Pikmin Bloom",
      "developer": "Niantic, Inc.",
      "icon": "https://play-lh.googleusercontent.com/lZhO5dn3aCCBkqfFBMCFQeTsCaCfKA_wdmXsco4HtZoy970MSPnXTSbm5Ub-Z3glHA",
      "score": 4.7980447,
      "ratings": 0,
      "category": "GAME",
      "url": "https://play.google.com/store/apps/details?id=com.nianticlabs.pikmin",
      "price": 0,
      "free": true,
      "platform": "android",
      "summary": "Walk on. Game on.",
      "updated": "2026-06-02",
      "released": "2021-10-27",
      "contentRating": "適合所有人"
    },
    {
      "rank": 4,
      "appId": "com.fox.jstwgp",
      "name": "青丘世界：緣起",
      "developer": "JOYSTAR GAME INFORMATION TECHNOLOGY CO.,LIMITED",
      "icon": "https://play-lh.googleusercontent.com/JXwSU9aYn442fV3rTBFJNE8505liF1jmYU9fZEWr1st3yuw7qcYaPWQ5TpjafEnVtuji2hulGmAGWuh7H58nVQ",
      "score": 4.483721,
      "ratings": 0,
      "category": "GAME",
      "url": "https://play.google.com/store/apps/details?id=com.fox.jstwgp",
      "price": 0,
      "free": true,
      "platform": "android"
    },
    {
      "rank": 5,
      "appId": "com.dreamgames.royalkingdom",
      "name": "Royal Kingdom",
      "developer": "Dream Games, Ltd.",
      "icon": "https://play-lh.googleusercontent.com/nAAF2bxrD2BeoM1IkUZ6qeRG_QGG_Rekrrh4VYQSMDeRa7FR8sWMWaHClID547XJ3D4",
      "score": 4.56873,
      "ratings": 0,
      "category": "GAME",
      "url": "https://play.google.com/store/apps/details?id=com.dreamgames.royalkingdom",
      "price": 0,
      "free": true,
      "platform": "android",
      "summary": "現在就加入理查國王，踏上精采絕倫的三消益智冒險之旅！",
      "updated": "2026-06-01",
      "released": "2024-11-20",
      "contentRating": "適合所有人"
    },
    {
      "rank": 6,
      "appId": "com.lmdgame.neostreetball.tw",
      "name": "超時空街球對決",
      "developer": "LMD Games",
      "icon": "https://play-lh.googleusercontent.com/OOvlOQbgRJ3Ude0bd53oVGXX8I-8xPp_YdhLMD-XGSJXkU6-ushdxl61mGx2dPuy_0tOpB4L3SLuHYLFXUE",
      "score": 3.9831932,
      "ratings": 0,
      "category": "GAME",
      "url": "https://play.google.com/store/apps/details?id=com.lmdgame.neostreetball.tw",
      "price": 0,
      "free": true,
      "platform": "android"
    },
    {
      "rank": 7,
      "appId": "com.fiveminlab.overgeared.hero.backpack.merge",
      "name": "Overgeared Hero: Merge RPG",
      "developer": "5minlab Corp.",
      "icon": "https://play-lh.googleusercontent.com/BtgYfxhrBRe8IpCbT2q_YBlSVxgQpkbmlUjOHK8QcPUwbqueAXlgXe_8PDbZWnRL1Ug_lOUCKXnjccaGDvYYzg",
      "score": 4.615894,
      "ratings": 0,
      "category": "GAME",
      "url": "https://play.google.com/store/apps/details?id=com.fiveminlab.overgeared.hero.backpack.merge",
      "price": 0,
      "free": true,
      "platform": "android",
      "summary": "像素風肉鴿 RPG！背包戰鬥策略對決，合成裝備，爭奪勝利！",
      "updated": "2026-06-01",
      "released": "2026-05-25",
      "contentRating": "適合所有人"
    },
    {
      "rank": 8,
      "appId": "com.ecffri.arrows",
      "name": "Arrows – Puzzle Escape",
      "developer": "Lessmore GmbH",
      "icon": "https://play-lh.googleusercontent.com/f3szQ-tBQ5FVtiO2hwnJ6Gg4LbckQ9qKD099oiFqlvDo78uaD85Zn9G4o-W9390XnQ",
      "score": 4.8033333,
      "ratings": 0,
      "category": "GAME",
      "url": "https://play.google.com/store/apps/details?id=com.ecffri.arrows",
      "price": 0,
      "free": true,
      "platform": "android",
      "summary": "清除所有箭頭！在這款趣味遊戲中解決邏輯謎題，考驗你的大腦！",
      "updated": "2026-05-28",
      "released": "2025-07-09",
      "contentRating": "適合所有人"
    },
    {
      "rank": 9,
      "appId": "com.sgyjl.andtw",
      "name": "三國異將錄-首週真送533抽",
      "developer": "DUSTY MUTUAL",
      "icon": "https://play-lh.googleusercontent.com/kPOiXroQROENz7-PExMEkHBSZs5cA--QMHWPj_c5layyjRfRANjJc5vNgvldTSJ_ZFIXcVlpVb_gyBXZ6ha86g",
      "score": 4.775862,
      "ratings": 0,
      "category": "GAME",
      "url": "https://play.google.com/store/apps/details?id=com.sgyjl.andtw",
      "price": 0,
      "free": true,
      "platform": "android"
    },
    {
      "rank": 10,
      "appId": "com.Gameplier.TheGhost",
      "name": "The Ghost - Multiplayer Horror",
      "developer": "Gameplier",
      "icon": "https://play-lh.googleusercontent.com/Fx3UqiYCSP9x8S-W10ht-f_W3UQGOZW0Oh4Z1yQEPqZj8o5wIrfAOxVurgFdOZbn2Mk",
      "score": 3.69,
      "ratings": 0,
      "category": "GAME",
      "url": "https://play.google.com/store/apps/details?id=com.Gameplier.TheGhost",
      "price": 0,
      "free": true,
      "platform": "android",
      "summary": "合作生存恐怖遊戲。和你的朋友一起玩。",
      "updated": "2026-01-23",
      "released": "2021-05-25",
      "contentRating": "適合青少年"
    },
    {
      "rank": 11,
      "appId": "jp.co.goodroid.hyper.busflow",
      "name": "Bus Traffic Fever!",
      "developer": "GOODROID,Inc.",
      "icon": "https://play-lh.googleusercontent.com/caBiKRTVr57KEWAwIEH8mIXsjwrC19mfST9tLXizP1nPI3WdT5bJwXVSSQDb6HWLMKPkhVwLKHmA9PGAcrTZ",
      "score": 4.627451,
      "ratings": 0,
      "category": "GAME",
      "url": "https://play.google.com/store/apps/details?id=jp.co.goodroid.hyper.busflow",
      "price": 0,
      "free": true,
      "platform": "android",
      "summary": "一款巴士載客益智遊戲，你需要安排巴士將乘客送到目的地。",
      "updated": "2026-05-26",
      "released": "2026-02-19",
      "contentRating": "適合所有人"
    },
    {
      "rank": 12,
      "appId": "com.puzzlegames.puzzlebrickslegend",
      "name": "Color Block: Combo Blast",
      "developer": "Ivy",
      "icon": "https://play-lh.googleusercontent.com/yYQ4QldM1Dclw1mK0sW1gJlwT6XJ05qPf6IGu9GtXc3kKfNj92PqdmkD8OFtRId75a5fuKkJ5X38b2qCl3QYeA",
      "score": 3.99,
      "ratings": 0,
      "category": "GAME",
      "url": "https://play.google.com/store/apps/details?id=com.puzzlegames.puzzlebrickslegend",
      "price": 0,
      "free": true,
      "platform": "android",
      "summary": "在 Color Block 經典方塊拼圖挑戰中，發現無盡樂趣。",
      "updated": "2026-06-02",
      "released": "2019-04-17",
      "contentRating": "適合所有人"
    },
    {
      "rank": 13,
      "appId": "com.block.juggle",
      "name": "Block Blast!",
      "developer": "HungryStudio",
      "icon": "https://play-lh.googleusercontent.com/R0qgNDYYHbRhw6JFsdEbDMqONplEvJx0m0W9wzYVvY3eNF1c2rfBWYjQxW0sLEzFe1E",
      "score": 4.5959663,
      "ratings": 0,
      "category": "GAME",
      "url": "https://play.google.com/store/apps/details?id=com.block.juggle",
      "price": 0,
      "free": true,
      "platform": "android",
      "summary": "玩轉方塊消消樂，暢享休閒好時光。時下熱門的益智小遊戲，離線可玩，樂趣無限！",
      "updated": "2026-06-03",
      "released": "2022-09-23",
      "contentRating": "適合所有人"
    },
    {
      "rank": 14,
      "appId": "com.roblox.client",
      "name": "Roblox",
      "developer": "Roblox Corporation",
      "icon": "https://play-lh.googleusercontent.com/7cIIPlWm4m7AGqVpEsIfyL-HW4cQla4ucXnfalMft1TMIYQIlf2vqgmthlZgbNAQoaQ",
      "score": 3.7170749,
      "ratings": 0,
      "category": "GAME",
      "url": "https://play.google.com/store/apps/details?id=com.roblox.client",
      "price": 0,
      "free": true,
      "platform": "android",
      "summary": "在數百萬個線上多人遊戲中暢玩、創作並連結。",
      "updated": "2026-05-28",
      "released": "2014-07-15",
      "contentRating": "適合青少年"
    },
    {
      "rank": 15,
      "appId": "com.voodoo.almanac",
      "name": "The Almanac",
      "developer": "VOODOO",
      "icon": "https://play-lh.googleusercontent.com/BqRixa3rlgWcQhxggNg2eoNUFej5boqphhgMLscLoOfLxT_E3cV-hcZ32DGHGTfTux2UHrpof3SwcB1goJYlUBs",
      "score": 4.875,
      "ratings": 0,
      "category": "GAME",
      "url": "https://play.google.com/store/apps/details?id=com.voodoo.almanac",
      "price": 0,
      "free": true,
      "platform": "android",
      "summary": "每天透過簡單、巧妙的邏輯挑戰來鍛鍊你的思維。",
      "updated": "2026-06-04",
      "released": "2025-11-13",
      "contentRating": "適合所有人"
    },
    {
      "rank": 16,
      "appId": "com.xman.tw.gp",
      "name": "超能戰爭",
      "developer": "Glaciers Game",
      "icon": "https://play-lh.googleusercontent.com/f2ccfY6_dMuiZqPE6AOcmAlgkND7fj23iLo84kDBGSzR7lnYkwqp8QG72X3JHi0MB8AGb4-PnXsyhI9-KsPt0w",
      "score": 4.589286,
      "ratings": 0,
      "category": "GAME",
      "url": "https://play.google.com/store/apps/details?id=com.xman.tw.gp",
      "price": 0,
      "free": true,
      "platform": "android",
      "summary": "揭開隱藏奧秘，體驗多樣策略",
      "updated": "2026-05-15",
      "released": "",
      "contentRating": "適合所有人"
    },
    {
      "rank": 17,
      "appId": "com.hidea.cat.magicrecipe",
      "name": "Cats&Soup : Merge Magic Recipe",
      "developer": "NEOWIZ",
      "icon": "https://play-lh.googleusercontent.com/qHWByE9RBxH48KpV_vxjjKvMqoA6qcT5MtztOoGv1hkIJoa0GA9Y8a1Od2ZuSaoN_2kK_nU48wH-2l7mUqGcgtM",
      "score": 4.714286,
      "ratings": 0,
      "category": "GAME",
      "url": "https://play.google.com/store/apps/details?id=com.hidea.cat.magicrecipe",
      "price": 0,
      "free": true,
      "platform": "android",
      "summary": "透過合併組合，打造魔法貓咪的家",
      "updated": "2026-06-02",
      "released": "2025-04-21",
      "contentRating": "適合所有人"
    },
    {
      "rank": 18,
      "appId": "com.snktkofxy.gp",
      "name": "SNK：全明星覺醒",
      "developer": "LIGHTYEAR MATRIX LIMITED",
      "icon": "https://play-lh.googleusercontent.com/i5ztEhzjDzfV0NbyXmMR-B5ySJG8bltorb6W3iN_Sh0TKG7yu50F3GbptuodeIJ2wqfLhKBwi22ActkoE8Db",
      "score": 4.6062994,
      "ratings": 0,
      "category": "GAME",
      "url": "https://play.google.com/store/apps/details?id=com.snktkofxy.gp",
      "price": 0,
      "free": true,
      "platform": "android"
    },
    {
      "rank": 19,
      "appId": "color.number.paint.pixle.art.sort.jigsaw",
      "name": "Jewel Coloring",
      "developer": "TaTa Game Technology Limited",
      "icon": "https://play-lh.googleusercontent.com/4O3eRZ4cOMPSFiasjvlJuodijaKtNiv7HZ9Hm5r4CT78imAL32QbbWoJkiOJ3erjS4Yi652WTBrwcQrbbsuW",
      "score": 4.90625,
      "ratings": 0,
      "category": "GAME",
      "url": "https://play.google.com/store/apps/details?id=color.number.paint.pixle.art.sort.jigsaw",
      "price": 0,
      "free": true,
      "platform": "android",
      "summary": "寶石著色：輕鬆休閒的寶石分類像素藝術益智遊戲。簡單易上手，老少咸宜。",
      "updated": "2026-06-02",
      "released": "2026-02-25",
      "contentRating": "適合所有人"
    },
    {
      "rank": 20,
      "appId": "com.readygo.dark.gp",
      "name": "Dark War Survival",
      "developer": "Omnilojo Pte Ltd",
      "icon": "https://play-lh.googleusercontent.com/gaanbGpciRZh801jTahoaImwr96KtBp2Uuez12ww9sIxFQhqieIZgTjB_dGzhCaR1ccM9Eku11FxhOWgoxifwdc",
      "score": 4.610559,
      "ratings": 0,
      "category": "GAME",
      "url": "https://play.google.com/store/apps/details?id=com.readygo.dark.gp",
      "price": 0,
      "free": true,
      "platform": "android",
      "summary": "建立避難所躲避喪屍末日、重新點亮人類文明的火種。",
      "updated": "2026-05-29",
      "released": "2024-05-19",
      "contentRating": "適合 10 歲以上"
    },
    {
      "rank": 21,
      "appId": "com.igs.TMD",
      "name": "滿貫大亨 - 快打旋風登場",
      "developer": "SHIZI TECH LTD CO.",
      "icon": "https://play-lh.googleusercontent.com/kQ57VWR8f1Bokb-NJCukqIIoM2noSW9BE2op59Dq8QiZhsCSDEoSModKcG028ncCvg",
      "score": 4.3713417,
      "ratings": 0,
      "category": "GAME",
      "url": "https://play.google.com/store/apps/details?id=com.igs.TMD",
      "price": 0,
      "free": true,
      "platform": "android",
      "summary": "Link&amp;Win新機「雷霆之錘2」超級奧丁之怒引爆全場，2000X球狂炸來襲！",
      "updated": "2026-05-23",
      "released": "2016-01-05",
      "contentRating": "適合青少年"
    },
    {
      "rank": 22,
      "appId": "com.daerigame.rellion",
      "name": "RELLION: NPC Survival",
      "developer": "DAERI SOFT Inc",
      "icon": "https://play-lh.googleusercontent.com/tP-kqTCorbXhgeOtwpQ996JKcPWHnS7pzc1nOPoJwCnvcRJ-VrVWPuUSb1LfpgEs00M",
      "score": 4.427586,
      "ratings": 0,
      "category": "GAME",
      "url": "https://play.google.com/store/apps/details?id=com.daerigame.rellion",
      "price": 0,
      "free": true,
      "platform": "android",
      "summary": "為了NPC的生存而進行的第900次嘗試。你的選擇將決定瑞利昂的命運！",
      "updated": "2026-06-03",
      "released": "2026-05-12",
      "contentRating": "適合 10 歲以上"
    },
    {
      "rank": 23,
      "appId": "tw.com.iwplay.nte",
      "name": "異環",
      "developer": "IWPLAY WORLD",
      "icon": "https://play-lh.googleusercontent.com/Sslrcaebh6rQ257vPZrXmt1vSdmUOAtIExZginE0T4iuLlDu-ZuS4kTtDHpeHZIxdqKHuuWMu9lzhR7BmHW4",
      "score": 4.584615,
      "ratings": 0,
      "category": "GAME",
      "url": "https://play.google.com/store/apps/details?id=tw.com.iwplay.nte",
      "price": 0,
      "free": true,
      "platform": "android"
    },
    {
      "rank": 24,
      "appId": "com.sniper3d.sfgame",
      "name": "Sniper 3D: Alien War",
      "developer": "KampfireGames",
      "icon": "https://play-lh.googleusercontent.com/rAZ7BknRWQKYyBUL3A93G9Jbl-MewLJiq-Ni6YUP9B3Jv9HiFTCROyXVeFyy8Qm2XcNK2OvZHYJFIjmRmKL7eHE",
      "score": 4.67541,
      "ratings": 0,
      "category": "GAME",
      "url": "https://play.google.com/store/apps/details?id=com.sniper3d.sfgame",
      "price": 0,
      "free": true,
      "platform": "android",
      "summary": "瞄準，射擊，命中！",
      "updated": "2026-03-06",
      "released": "2026-01-11",
      "contentRating": "適合青少年"
    },
    {
      "rank": 25,
      "appId": "com.flower.forest.word.puzzle",
      "name": "Flower Forest - Word Puzzle",
      "developer": "SkySoft Studio",
      "icon": "https://play-lh.googleusercontent.com/85UQPJ5ABPQ5zUEWlEU3Xv1dfqmVX5tqsD7YPKmOJWsXonblfTSM7rqtoWxns-VCQ-jhUDQfb8geUFOrZJDc",
      "score": 4.6181817,
      "ratings": 0,
      "category": "GAME",
      "url": "https://play.google.com/store/apps/details?id=com.flower.forest.word.puzzle",
      "price": 0,
      "free": true,
      "platform": "android",
      "summary": "夢幻般的解謎遊戲，你需要組合各種物品來解開超現實的謎題。",
      "updated": "2026-06-03",
      "released": "2026-05-03",
      "contentRating": "適合所有人"
    },
    {
      "rank": 26,
      "appId": "com.brain.logic.joygame",
      "name": "Brain Puzzle 2: Logic Twist",
      "developer": "JoyGame Studio",
      "icon": "https://play-lh.googleusercontent.com/q19v_2ZYEOdWOt6ABAVCl10zHrft5qkChjAwxtByGKxJxE3gNULQGf3BwsCYVJk4Jbhf",
      "score": 4.76,
      "ratings": 0,
      "category": "GAME",
      "url": "https://play.google.com/store/apps/details?id=com.brain.logic.joygame",
      "price": 0,
      "free": true,
      "platform": "android",
      "summary": "準備好重返這個充滿瘋狂轉折與燒腦樂趣的世界吧！",
      "updated": "2026-05-19",
      "released": "2025-05-21",
      "contentRating": "適合青少年"
    },
    {
      "rank": 27,
      "appId": "com.hortor.femsj.asia",
      "name": "肥鵝美食街",
      "developer": "hortor games",
      "icon": "https://play-lh.googleusercontent.com/Oj6Pdmq3VXc3TiKXr3HnRHi4rh2Lw2GmHrqMilG1gjHVwCFxuQDHPkn8D5Ny8_8qmvPCF9jpEP87sZsOz3nq_w",
      "score": 4.7009344,
      "ratings": 0,
      "category": "GAME",
      "url": "https://play.google.com/store/apps/details?id=com.hortor.femsj.asia",
      "price": 0,
      "free": true,
      "platform": "android",
      "summary": "合成美食，經營小店。",
      "updated": "2026-05-20",
      "released": "",
      "contentRating": "適合所有人"
    },
    {
      "rank": 28,
      "appId": "com.playnest.jadecourt",
      "name": "亂世美人傳",
      "developer": "PLAYNEST LIMITED",
      "icon": "https://play-lh.googleusercontent.com/9itI6aJnXxoY3a8T9N8-ySvqvC3WJnskI7oORLig2KpqRmb6zJ1ZF0ETUa7s3cjk7KWGwglfcxn0rC4AJQsrrhg",
      "score": 4.7272725,
      "ratings": 0,
      "category": "GAME",
      "url": "https://play.google.com/store/apps/details?id=com.playnest.jadecourt",
      "price": 0,
      "free": true,
      "platform": "android",
      "summary": "一款融合華夏五千年文化、古風美術、多時代英雄、策略佈陣、美人養成的戰略手機遊戲",
      "updated": "2026-04-30",
      "released": "",
      "contentRating": "適合青少年"
    },
    {
      "rank": 29,
      "appId": "com.run.tower.defense",
      "name": "Kingshot",
      "developer": "Century Games PTE. LTD.",
      "icon": "https://play-lh.googleusercontent.com/DLovyLDLznCbkDw39T-d9BUXkDbUjO9ne3_eJyA27IcfgIXR2Hmu3HqEDlYxGXnwrp0",
      "score": 4.511324,
      "ratings": 0,
      "category": "GAME",
      "url": "https://play.google.com/store/apps/details?id=com.run.tower.defense",
      "price": 0,
      "free": true,
      "platform": "android",
      "summary": "輕鬆放置SLG，征服中世紀",
      "updated": "2026-04-22",
      "released": "2025-03-03",
      "contentRating": "適合 10 歲以上"
    },
    {
      "rank": 30,
      "appId": "com.u1.relax.minigame3",
      "name": "Mini Challenges: Calm Games",
      "developer": "UltraPub",
      "icon": "https://play-lh.googleusercontent.com/tZO4p-R6R05mZAMKsEmH6shCtolDdhgkn2CwtyNOGd6PSBGU1RNH3l3SjkBOrHWD9nA",
      "score": 4.826087,
      "ratings": 0,
      "category": "GAME",
      "url": "https://play.google.com/store/apps/details?id=com.u1.relax.minigame3",
      "price": 0,
      "free": true,
      "platform": "android",
      "summary": "減壓遊戲集合：趣味十足、輕鬆舒緩的益智遊戲，點擊即可放鬆身心",
      "updated": "2026-06-04",
      "released": "2026-01-22",
      "contentRating": "適合所有人"
    },
    {
      "rank": 31,
      "appId": "com.rpg.match.hero.teewee",
      "name": "Match Go! Heroes",
      "developer": "TEEWEE LIMITED",
      "icon": "https://play-lh.googleusercontent.com/6MCsijVmqbUmHC7OKPPxaLPBF2SQt7BjspEKKADnEXwyTTXV-32MAyCz-4xxlc52REydSB2d6cYgPzOYlxEARac",
      "score": 3.0769231,
      "ratings": 0,
      "category": "GAME",
      "url": "https://play.google.com/store/apps/details?id=com.rpg.match.hero.teewee",
      "price": 0,
      "free": true,
      "platform": "android"
    },
    {
      "rank": 32,
      "appId": "com.garena.game.df",
      "name": "Garena® Delta Force",
      "developer": "Garena Mobile Private Limited",
      "icon": "https://play-lh.googleusercontent.com/utG-EAUp93da_Bp0-AeOS7M8xYWRcSYhjIcxKFxhfcSU32moPHIhL9IS-AT20gaJ8w",
      "score": 4.011757,
      "ratings": 0,
      "category": "GAME",
      "url": "https://play.google.com/store/apps/details?id=com.garena.game.df",
      "price": 0,
      "free": true,
      "platform": "android",
      "summary": "爽感爆棚、最受歡迎的搜打撤射擊遊戲首選 手機、電腦上跨平台同步進度激戰射擊！",
      "updated": "2026-04-13",
      "released": "",
      "contentRating": "適合青少年"
    },
    {
      "rank": 33,
      "appId": "com.vitastudio.mahjong",
      "name": "Vita Mahjong",
      "developer": "Vita Studio.",
      "icon": "https://play-lh.googleusercontent.com/RETWTV6fTThcDWtsRJqDJ14c_plFWlByxP6MEcvJmvyKwl7YBCiPQ8HQIp-CBDZjOHQ",
      "score": 4.814677,
      "ratings": 0,
      "category": "GAME",
      "url": "https://play.google.com/store/apps/details?id=com.vitastudio.mahjong",
      "price": 0,
      "free": true,
      "platform": "android",
      "summary": "玩大塊麻將接龍：透過經典配對益智遊戲放鬆身心！",
      "updated": "2026-05-26",
      "released": "2024-01-09",
      "contentRating": "適合所有人"
    },
    {
      "rank": 34,
      "appId": "com.gof.global",
      "name": "Whiteout Survival",
      "developer": "Century Games PTE. LTD.",
      "icon": "https://play-lh.googleusercontent.com/gtcDOls1xCaV_qtRKx3dsk75bNBqel81gWkhK2xvgq5KKHj_71lnZjXYO6He97w0j-U",
      "score": 4.4122176,
      "ratings": 0,
      "category": "GAME",
      "url": "https://play.google.com/store/apps/details?id=com.gof.global",
      "price": 0,
      "free": true,
      "platform": "android",
      "summary": "三億人都在玩的原創冰雪手遊",
      "updated": "2026-04-09",
      "released": "2023-02-09",
      "contentRating": "適合 10 歲以上"
    },
    {
      "rank": 35,
      "appId": "com.mover.twrxjhw",
      "name": "新熱血江湖：世界",
      "developer": "Mover Games Limited",
      "icon": "https://play-lh.googleusercontent.com/QSa9Wy-tw3K06y21JBX6nECAQHys53WfyJqtUGQbpJ_IIt4QdZ6KLe1ApFKzv_b-7kV7S3KRCByFX2Pa4UhZOQ",
      "score": 4.7491164,
      "ratings": 0,
      "category": "GAME",
      "url": "https://play.google.com/store/apps/details?id=com.mover.twrxjhw",
      "price": 0,
      "free": true,
      "platform": "android"
    },
    {
      "rank": 36,
      "appId": "com.oakever.arrows",
      "name": "Arrows GO!",
      "developer": "Oakever Games",
      "icon": "https://play-lh.googleusercontent.com/zWEc5_IxvR2HnOLWkqa7Vszuvzg8G3OZXH1hvZy-S-ne6HsJRHOoi1y4w4_0JemVsaCE",
      "score": 4.5825243,
      "ratings": 0,
      "category": "GAME",
      "url": "https://play.google.com/store/apps/details?id=com.oakever.arrows",
      "price": 0,
      "free": true,
      "platform": "android",
      "summary": "清除箭頭、解開謎題，並鍛鍊你的大腦。",
      "updated": "2026-05-28",
      "released": "2026-02-13",
      "contentRating": "適合所有人"
    },
    {
      "rank": 37,
      "appId": "beats.color.sing.star.rush",
      "name": "Magic Level 9 Music Piano Game",
      "developer": "Beatwave Studio",
      "icon": "https://play-lh.googleusercontent.com/uIih37VSDcSfq-Fp2ve2BGmBSLGEVD_AZj1_dI7_GeJLUuHxh-sgNBCIPEt5Axt98T-x",
      "score": 4.58125,
      "ratings": 0,
      "category": "GAME",
      "url": "https://play.google.com/store/apps/details?id=beats.color.sing.star.rush",
      "price": 0,
      "free": true,
      "platform": "android",
      "summary": "您的鋼琴遊戲中有所有熱門歌曲嗎 解鎖節奏魔法與主題！最適合所有年齡的音樂愛好者！感受魔力，不要錯過瓷磚",
      "updated": "2026-06-02",
      "released": "2025-06-14",
      "contentRating": "適合所有人"
    },
    {
      "rank": 38,
      "appId": "com.grandgames.magicsort",
      "name": "Magic Sort!",
      "developer": "Grand Games A.Ş.",
      "icon": "https://play-lh.googleusercontent.com/WpTMBQdhAVa2y3tzsw5T4h9aT5C9Ng1fo3m5JGp0fi4bCD3Gcw8hOPodjjbs2moXX71FH21eSfPMVpR3OL6B",
      "score": 4.4905663,
      "ratings": 0,
      "category": "GAME",
      "url": "https://play.google.com/store/apps/details?id=com.grandgames.magicsort",
      "price": 0,
      "free": true,
      "platform": "android",
      "summary": "水分類拼圖",
      "updated": "2026-05-23",
      "released": "2024-06-26",
      "contentRating": "適合所有人"
    },
    {
      "rank": 39,
      "appId": "com.game.thatsmyseat",
      "name": "That's My Seat - Logic Puzzle",
      "developer": "Rooftop Game",
      "icon": "https://play-lh.googleusercontent.com/8rv5APO27lQ23ppa3R0vL3N1M6dBa8_pdFLnCmiRlGDQxQVMyIbkdp71VIVxBhu99z9x",
      "score": 4.6605506,
      "ratings": 0,
      "category": "GAME",
      "url": "https://play.google.com/store/apps/details?id=com.game.thatsmyseat",
      "price": 0,
      "free": true,
      "platform": "android",
      "summary": "百变福尔摩斯，谁占了我的座？",
      "updated": "2026-05-22",
      "released": "2024-08-15",
      "contentRating": "適合所有人"
    },
    {
      "rank": 40,
      "appId": "com.nebula.mahjongtile",
      "name": "Mahjong Blast",
      "developer": "Nebula  Studio",
      "icon": "https://play-lh.googleusercontent.com/2oyx82631YlAGY6QPOoGXMJUhnXpCIJflKgx438f1eDwmqM1kbScltnPU0R-mgykkvM4H2COx6sQk3S9cnOblwg",
      "score": 4.8939395,
      "ratings": 0,
      "category": "GAME",
      "url": "https://play.google.com/store/apps/details?id=com.nebula.mahjongtile",
      "price": 0,
      "free": true,
      "platform": "android",
      "summary": "經典單機麻將配對遊戲，離線無廣告，休閒減壓的麻將連連看益智佳作",
      "updated": "2026-06-04",
      "released": "2025-06-23",
      "contentRating": "適合所有人"
    },
    {
      "rank": 41,
      "appId": "com.hwyk.tricky2",
      "name": "Tricky Puzzle 2: Brain Test",
      "developer": "YIKE TECHNOLOGY LIMITED",
      "icon": "https://play-lh.googleusercontent.com/a6V1_XroAfESHIAn6CRJl8No7K_UO1W0GNjExWaZUHX7iRlsqxmEEFTPd_eijuZ8hmBxG3MgUN95kafaypeo__Y",
      "score": 4.787879,
      "ratings": 0,
      "category": "GAME",
      "url": "https://play.google.com/store/apps/details?id=com.hwyk.tricky2",
      "price": 0,
      "free": true,
      "platform": "android",
      "summary": "解開各種腦洞謎題，挑戰你的思維極限！",
      "updated": "2026-05-29",
      "released": "2026-03-22",
      "contentRating": "適合青少年"
    },
    {
      "rank": 42,
      "appId": "com.wood.bolt.wordle.screw.nuts.puzzle",
      "name": "Woodle Screw™ Pin Nuts & Bolts",
      "developer": "LifePulse Puzzle Game Studio",
      "icon": "https://play-lh.googleusercontent.com/3l5HiW1HL3MT86rgAJrCZ6SpuCOxm9I4gxKS8in8mAsz1RXr2AyRt63QaXQ57Kx6-DutV11MvDsEdX41MnzNb9A",
      "score": 4.854195,
      "ratings": 0,
      "category": "GAME",
      "url": "https://play.google.com/store/apps/details?id=com.wood.bolt.wordle.screw.nuts.puzzle",
      "price": 0,
      "free": true,
      "platform": "android",
      "summary": "解決木製主題的螺絲難題，並對各種顏色的螺絲釘進行分類！挑戰並考驗您的智慧。",
      "updated": "2026-05-14",
      "released": "2024-10-23",
      "contentRating": "適合 10 歲以上"
    },
    {
      "rank": 43,
      "appId": "com.wood.block.sudoku.puzzle.bm",
      "name": "Block Crush - Wood Block Blast",
      "developer": "Wonderful  Studio",
      "icon": "https://play-lh.googleusercontent.com/f_ImrzQpXw781wa_yNSxhfJz4b_t-MSQ6A1PXPoFBX3b0BkKRwVc7ik4eVbwA-x5S0jRxpZ0KvD__ULeEFwFAw",
      "score": 4.80035,
      "ratings": 0,
      "category": "GAME",
      "url": "https://play.google.com/store/apps/details?id=com.wood.block.sudoku.puzzle.bm",
      "price": 0,
      "free": true,
      "platform": "android",
      "summary": "專注與放鬆兼具，體驗木質方塊的溫暖與療癒。",
      "updated": "2026-06-03",
      "released": "2021-12-14",
      "contentRating": "適合所有人"
    },
    {
      "rank": 44,
      "appId": "com.cseightworld.google",
      "name": "打寳傳説：神話篇",
      "developer": "Star Entertainment HK",
      "icon": "https://play-lh.googleusercontent.com/J_RNKUJLf6lW321Iz4Is9x42bYf0thIJWy4iaxj1hbp7LPPmB5yE4y2S0gqPITdAkDxcmcK9klxJi2zMVHxD9w",
      "score": 4.451923,
      "ratings": 0,
      "category": "GAME",
      "url": "https://play.google.com/store/apps/details?id=com.cseightworld.google",
      "price": 0,
      "free": true,
      "platform": "android"
    },
    {
      "rank": 45,
      "appId": "com.epicoro.castleclashers",
      "name": "Castle Busters",
      "developer": "VOODOO",
      "icon": "https://play-lh.googleusercontent.com/VW7o5ybPRq9TbTQs9_pzrJkYoFk4QVxUkV96bVfauDmGBZ8O6KNHIRH4oIRlkQAgogw",
      "score": 4.1773047,
      "ratings": 0,
      "category": "GAME",
      "url": "https://play.google.com/store/apps/details?id=com.epicoro.castleclashers",
      "price": 0,
      "free": true,
      "platform": "android",
      "summary": "即時1v1 PvP策略格鬥遊戲。摧毀城堡、攻城塔，稱霸競技場！",
      "updated": "2026-06-03",
      "released": "2025-07-18",
      "contentRating": "適合青少年"
    },
    {
      "rank": 46,
      "appId": "com.moonactive.cmboard",
      "name": "Coin Master - Board Adventure",
      "developer": "Moon Active",
      "icon": "https://play-lh.googleusercontent.com/pFMYxxHpIsLKeaxO9wjVRpAsgMaLKbT1kPwofNQtGi69-6fF_eUyIViAMY66auDrvsJnw2h6S5rpF8XaZcrm",
      "score": 4.699029,
      "ratings": 0,
      "category": "GAME",
      "url": "https://play.google.com/store/apps/details?id=com.moonactive.cmboard",
      "price": 0,
      "free": true,
      "platform": "android",
      "summary": "投擲骰子，建造城鎮，打破好友的高分紀錄！",
      "updated": "2026-05-29",
      "released": "2026-02-05",
      "contentRating": "適合所有人"
    },
    {
      "rank": 47,
      "appId": "com.floralgames.hjxp",
      "name": "我的花園世界 - 玩遊戲送鮮花",
      "developer": "FLORAL GAMES LIMITED",
      "icon": "https://play-lh.googleusercontent.com/S9zzvkY2cne-Gt-9rKjt2_Mo8mQsaVggjJeex4OB6PP-Qd4R6d0FLhk0MUE70FH7JX4x5Dtd3EW0h1QK1ZsVk-o",
      "score": 4.3820224,
      "ratings": 0,
      "category": "GAME",
      "url": "https://play.google.com/store/apps/details?id=com.floralgames.hjxp",
      "price": 0,
      "free": true,
      "platform": "android",
      "summary": "已累計成功配送超過 30,000 束鮮花。全台港澳配送，真的送、天天送！",
      "updated": "2026-05-20",
      "released": "",
      "contentRating": "適合青少年"
    },
    {
      "rank": 48,
      "appId": "com.studiobside.starMain",
      "name": "StarSavior",
      "developer": "STUDIOBSIDE",
      "icon": "https://play-lh.googleusercontent.com/d2Slgi-LBwMHefTKnqYruKIUEJFXC6RPYXEnDhYcyp3fm9IcNrxuKH1ofljXjs1U2v12fBsWhTTYhciDOLyilEg",
      "score": 4.638889,
      "ratings": 0,
      "category": "GAME",
      "url": "https://play.google.com/store/apps/details?id=com.studiobside.starMain",
      "price": 0,
      "free": true,
      "platform": "android",
      "summary": "星辰寄宿的救援者育成物語",
      "updated": "2026-05-29",
      "released": "2026-03-17",
      "contentRating": "適合青少年"
    },
    {
      "rank": 49,
      "appId": "com.fun.brain.game",
      "name": "Brain Puzzle: Tricky Quest",
      "developer": "JoyGame Studio",
      "icon": "https://play-lh.googleusercontent.com/OOpJ60wKFvTxOdGj2VTkU2D-dWn2z6ggJbev6q4-yJPIqFWPywJ1oJajnWWvh8zASV4EiZHlHWy4FmTDJvR_QWc",
      "score": 4.7027025,
      "ratings": 0,
      "category": "GAME",
      "url": "https://play.google.com/store/apps/details?id=com.fun.brain.game",
      "price": 0,
      "free": true,
      "platform": "android",
      "summary": "一款燒腦的找茬和解謎遊戲，盡情釋放你的腦洞和創意！",
      "updated": "2026-04-29",
      "released": "2024-06-20",
      "contentRating": "適合青少年"
    },
    {
      "rank": 50,
      "appId": "com.panstudio.gplay.duetnightabyss.arpg.global",
      "name": "Duet Night Abyss",
      "developer": "Hong Kong Spiral Rising Technology Co., Limited",
      "icon": "https://play-lh.googleusercontent.com/wNyltcXoUMKz7txb1KGz0MN4-B-HXv6-iVC6n39cry5FNukJxtoJyQ-sC-KMrg-CNO1a_Ed3r8AaUJNuHWGsjA",
      "score": 3.6666667,
      "ratings": 0,
      "category": "GAME",
      "url": "https://play.google.com/store/apps/details?id=com.panstudio.gplay.duetnightabyss.arpg.global",
      "price": 0,
      "free": true,
      "platform": "android"
    },
    {
      "rank": 51,
      "appId": "com.igs.starparty.aos",
      "name": "玩星派對",
      "developer": "GAMEJOY TECHNOLOGY CO",
      "icon": "https://play-lh.googleusercontent.com/74nTE4rbHO83nJkSgfp6ZptOnwatXqkKE-ioQjcjzkDgYFJyKgluZd0R1g13Q-8zwE_MZtNU7fznTafMlJFRtzY",
      "score": 4.519071,
      "ratings": 0,
      "category": "GAME",
      "url": "https://play.google.com/store/apps/details?id=com.igs.starparty.aos",
      "price": 0,
      "free": true,
      "platform": "android"
    },
    {
      "rank": 52,
      "appId": "com.yzzg.mdgame",
      "name": "暗影紀元-魔幻冒险之旅",
      "developer": "Zonfun Entertainment",
      "icon": "https://play-lh.googleusercontent.com/5qyS-el7YsLUY3OeoXgM1SGTWB-0ssaKdbOTghxBvwVPB1BP5MH4IBFe6YM8RejEwk0gYWzDX4bxpv9-Z36sSw",
      "score": 4.585492,
      "ratings": 0,
      "category": "GAME",
      "url": "https://play.google.com/store/apps/details?id=com.yzzg.mdgame",
      "price": 0,
      "free": true,
      "platform": "android"
    },
    {
      "rank": 53,
      "appId": "sheep.animal.parking.puzzle.game.jam",
      "name": "Sheep Dash: Sheep Away",
      "developer": "Snap Brain Games",
      "icon": "https://play-lh.googleusercontent.com/kl66iWEo6PaSHzE3Gp4oYx22-Kn4REFbQborB288N4le8ErrHIXRn6wINcJVfDnXo4zLZAOjdoRVyDuD7G9X",
      "score": 4.9040403,
      "ratings": 0,
      "category": "GAME",
      "url": "https://play.google.com/store/apps/details?id=sheep.animal.parking.puzzle.game.jam",
      "price": 0,
      "free": true,
      "platform": "android"
    },
    {
      "rank": 54,
      "appId": "com.funnyjoy.snysw.an",
      "name": "Brain Puzzle King",
      "developer": "Mangoing Game Studio",
      "icon": "https://play-lh.googleusercontent.com/OqtUPFO-s6YBenfAZVso0kgY3etTM6c6-dr7FMJVCzi_c9_wTNGso07hT1O5NaqfiYQ",
      "score": 4.3715672,
      "ratings": 0,
      "category": "GAME",
      "url": "https://play.google.com/store/apps/details?id=com.funnyjoy.snysw.an",
      "price": 0,
      "free": true,
      "platform": "android"
    },
    {
      "rank": 55,
      "appId": "com.nianticlabs.pokemongo",
      "name": "Pokémon GO",
      "developer": "Niantic, Inc.",
      "icon": "https://play-lh.googleusercontent.com/N3ayE1feuNfItNVRR7m6tTk7Wqnn6tNy0elJ8kdV3ITwgKBvHH0dk1e_vup8yFfzvlwPclduzsB8ZsqFBMjJEw",
      "score": 3.798245,
      "ratings": 0,
      "category": "GAME",
      "url": "https://play.google.com/store/apps/details?id=com.nianticlabs.pokemongo",
      "price": 0,
      "free": true,
      "platform": "android"
    },
    {
      "rank": 56,
      "appId": "com.nintendo.zana",
      "name": "Pictonico!",
      "developer": "Nintendo Co., Ltd.",
      "icon": "https://play-lh.googleusercontent.com/95Moc1fyNQ-fmn0yunSlaCJdAUTUqyyq-eSN7nCfTgJ9jrJoLopjgX37GIPeT5m_igbph-c577vX5xc87GJkbA",
      "score": 4.743243,
      "ratings": 0,
      "category": "GAME",
      "url": "https://play.google.com/store/apps/details?id=com.nintendo.zana",
      "price": 0,
      "free": true,
      "platform": "android"
    },
    {
      "rank": 57,
      "appId": "com.wildcaly.chbaseball.jkt",
      "name": "MLB CLUTCH HIT BASEBALL 26",
      "developer": "Wild Caly PTE. LTD.",
      "icon": "https://play-lh.googleusercontent.com/v8-XSy_H9fIFZAj4dLFyivSyxXeOaycWzKCN-m_k3qLGDW75OCelRucRkmgtbNqdA_KrUS2Ckbr1WsaXZ947nw",
      "score": 4.9166665,
      "ratings": 0,
      "category": "GAME",
      "url": "https://play.google.com/store/apps/details?id=com.wildcaly.chbaseball.jkt",
      "price": 0,
      "free": true,
      "platform": "android"
    },
    {
      "rank": 58,
      "appId": "com.ventogames.findthecat",
      "name": "Find The Cat - Spot It!",
      "developer": "Agave Games",
      "icon": "https://play-lh.googleusercontent.com/JVUrYb53YKB2WTdq4OXnFELdD3FqjDqZxayl9Hnzgxx-7rx_6I3NQ7j_VjCxegOz6QhFOdUAbtfejfv1siyJgQ",
      "score": 4.9085197,
      "ratings": 0,
      "category": "GAME",
      "url": "https://play.google.com/store/apps/details?id=com.ventogames.findthecat",
      "price": 0,
      "free": true,
      "platform": "android"
    },
    {
      "rank": 59,
      "appId": "com.arrow.madness.games.arrows.escape.puzzle.game",
      "name": "Arrow Puzzle - Arrow Madness",
      "developer": "Ashita Games",
      "icon": "https://play-lh.googleusercontent.com/MSgmgS1OOkycJ1l3WcfKb8V9ZVX1we6iakmmOpSThBVXo-ud0AIahQIG2tamxYWVmI0",
      "score": 4.9166665,
      "ratings": 0,
      "category": "GAME",
      "url": "https://play.google.com/store/apps/details?id=com.arrow.madness.games.arrows.escape.puzzle.game",
      "price": 0,
      "free": true,
      "platform": "android"
    },
    {
      "rank": 60,
      "appId": "com.ApacheGunnerGames.PoolroomsTheHiddenExit",
      "name": "Poolrooms: The Hidden Exit",
      "developer": "Apache Gunner Games",
      "icon": "https://play-lh.googleusercontent.com/dTW6_Z_EG9JO18_VHK88nn5kxwbBeV4lavunrt3sj97OUmhNd2hFlzDDEFRsUwqCX4A",
      "score": 4.6041665,
      "ratings": 0,
      "category": "GAME",
      "url": "https://play.google.com/store/apps/details?id=com.ApacheGunnerGames.PoolroomsTheHiddenExit",
      "price": 0,
      "free": true,
      "platform": "android"
    },
    {
      "rank": 61,
      "appId": "com.dl.defender",
      "name": "Fortivale Defenders",
      "developer": "DrDe",
      "icon": "https://play-lh.googleusercontent.com/sF5UHZNGkxPe7GLhbMzYIi3zNrYz6ODC575_vO-T3tkNzITxqhU-4dyXxfzg8RX04dsYBoJWzPR48xp7amA7XTA",
      "score": 3.4,
      "ratings": 0,
      "category": "GAME",
      "url": "https://play.google.com/store/apps/details?id=com.dl.defender",
      "price": 0,
      "free": true,
      "platform": "android"
    },
    {
      "rank": 62,
      "appId": "block.color.game.jam.blocks.sort.puzzle.games.slide.free",
      "name": "Block Color Mania, Puzzle Game",
      "developer": "Brainteaser Puzzle Game Studio",
      "icon": "https://play-lh.googleusercontent.com/fJ_pK4YX0tLme8wE7uBkRIiLtwKQTFaSQaqgNezutmVwOMrbv06lvPiHoGsAP6ApOw",
      "score": 4.88,
      "ratings": 0,
      "category": "GAME",
      "url": "https://play.google.com/store/apps/details?id=block.color.game.jam.blocks.sort.puzzle.games.slide.free",
      "price": 0,
      "free": true,
      "platform": "android"
    },
    {
      "rank": 63,
      "appId": "com.nexon.ma",
      "name": "MapleStory : Idle RPG",
      "developer": "NEXON Company",
      "icon": "https://play-lh.googleusercontent.com/lJzKrVodZ9QBZDaIbO3-xGSgMvXgo87p3UjH9uNAU9XGlmSN0-GrRakPuekVSultgbyxsK8jALuWEObln2QE",
      "score": 4.4864078,
      "ratings": 0,
      "category": "GAME",
      "url": "https://play.google.com/store/apps/details?id=com.nexon.ma",
      "price": 0,
      "free": true,
      "platform": "android"
    },
    {
      "rank": 64,
      "appId": "com.cool.adult.tile.mahjongcrush",
      "name": "Mahjong Crush",
      "developer": "Dynamic Aviation Group, Inc.",
      "icon": "https://play-lh.googleusercontent.com/3Iwo-rNx9FKv2MKO__sUTTK0HkCv_nvDxWi7Pwmm6jXOmFBFamKdPkUEoTZUGLvd97i5T7pnDvrIUccC3Ancqg",
      "score": 4.7105265,
      "ratings": 0,
      "category": "GAME",
      "url": "https://play.google.com/store/apps/details?id=com.cool.adult.tile.mahjongcrush",
      "price": 0,
      "free": true,
      "platform": "android"
    },
    {
      "rank": 65,
      "appId": "com.mergegames.gossipharbor",
      "name": "Gossip Harbor®: Merge & Story",
      "developer": "Microfun Limited",
      "icon": "https://play-lh.googleusercontent.com/PmMSCDLMab3nn0wj14BFZNqPncr1C14M5VmUrM3aXNmeRa1zEhNI4N3L1F1oO3qDYRPOQigQOyXxwDuQZZvTwA",
      "score": 4.379418,
      "ratings": 0,
      "category": "GAME",
      "url": "https://play.google.com/store/apps/details?id=com.mergegames.gossipharbor",
      "price": 0,
      "free": true,
      "platform": "android"
    },
    {
      "rank": 66,
      "appId": "com.sanctumstudio.poly",
      "name": "拉蒂亞的骰子之旅 - 療癒系冒險RPG",
      "developer": "Sanctum Games Limited",
      "icon": "https://play-lh.googleusercontent.com/l6VIeFPptMKq1oQo5GPd_3kwAbclwVMZxGNc9a25ApGCTK-1oTM3h1sD7RSpt3vnEps",
      "score": 4.5789475,
      "ratings": 0,
      "category": "GAME",
      "url": "https://play.google.com/store/apps/details?id=com.sanctumstudio.poly",
      "price": 0,
      "free": true,
      "platform": "android"
    },
    {
      "rank": 67,
      "appId": "com.TornadoBear.WayofKings",
      "name": "Path of Kings",
      "developer": "VOODOO",
      "icon": "https://play-lh.googleusercontent.com/VcS_RohO0ubQr885QfGZJnWjC15lI4wc0Rpolxc_PkSjLpsbmX39zcZFJkUuPuXUGdGP2j-ohtweQs_5w7-4iw",
      "score": 4.654412,
      "ratings": 0,
      "category": "GAME",
      "url": "https://play.google.com/store/apps/details?id=com.TornadoBear.WayofKings",
      "price": 0,
      "free": true,
      "platform": "android"
    },
    {
      "rank": 68,
      "appId": "com.pixel.art.coloring.color.number",
      "name": "Happy Color®: Color by Number",
      "developer": "X-FLOW",
      "icon": "https://play-lh.googleusercontent.com/paB5-2s6q3uXd3nRE0-2QzCLeLklmemDepD0_Erald5YQUazuiOhMvJ8giFluMAX0w",
      "score": 4.64437,
      "ratings": 0,
      "category": "GAME",
      "url": "https://play.google.com/store/apps/details?id=com.pixel.art.coloring.color.number",
      "price": 0,
      "free": true,
      "platform": "android"
    },
    {
      "rank": 69,
      "appId": "com.fatmerge.global",
      "name": "Tasty Travels: Merge Game",
      "developer": "Century Games PTE. LTD.",
      "icon": "https://play-lh.googleusercontent.com/wp39_3LiSinjfgFXdJLqKLCKEOUFglzQtK7UNhQPUlean7sdeAJu9qUM6fb6OHPpzFU",
      "score": 4.5133333,
      "ratings": 0,
      "category": "GAME",
      "url": "https://play.google.com/store/apps/details?id=com.fatmerge.global",
      "price": 0,
      "free": true,
      "platform": "android"
    },
    {
      "rank": 70,
      "appId": "com.hollywood.merge",
      "name": "Hollywood Merge",
      "developer": "VoyagerOne IE",
      "icon": "https://play-lh.googleusercontent.com/UCB8C2kwzgBnZQoiTcPvha4gmZBhET41ArNFmz9Kz1L56iRQJgLppcAdUN8n9PmaF4I",
      "score": 4.8,
      "ratings": 0,
      "category": "GAME",
      "url": "https://play.google.com/store/apps/details?id=com.hollywood.merge",
      "price": 0,
      "free": true,
      "platform": "android"
    },
    {
      "rank": 71,
      "appId": "com.screenshake.dominodreams",
      "name": "Domino Dreams™",
      "developer": "SuperPlay.",
      "icon": "https://play-lh.googleusercontent.com/KPBcFtNGNn3cMtgFthtbrWL0COVs5bINj1aQYniBa6JxgI-FAkce2czhVONttEtLQXnfd0X5rHA6YGMHp3nfWw",
      "score": 4.765714,
      "ratings": 0,
      "category": "GAME",
      "url": "https://play.google.com/store/apps/details?id=com.screenshake.dominodreams",
      "price": 0,
      "free": true,
      "platform": "android"
    },
    {
      "rank": 72,
      "appId": "com.shimmerstudio.kz",
      "name": "Hello! My Cozy Inn",
      "developer": "Shimmer Studio",
      "icon": "https://play-lh.googleusercontent.com/o1jgKWbgwZhl2p79MaiAj3xiQrIAtHVkLmtd8aAHib3cyYzcNwhqLqy5EcTLPa4__r39dx1CHhvs1ZArJeoGfA",
      "score": 4.828,
      "ratings": 0,
      "category": "GAME",
      "url": "https://play.google.com/store/apps/details?id=com.shimmerstudio.kz",
      "price": 0,
      "free": true,
      "platform": "android"
    },
    {
      "rank": 73,
      "appId": "com.tg.zjxsc2.tw",
      "name": "不正經魔王軍",
      "developer": "俠米遊戲",
      "icon": "https://play-lh.googleusercontent.com/YrgEiMQjJQXvZYGzPGrKK6VJX5fHJmZFifgO1prQzVCmhG39NBQtgyI_dFV8wa4fb5O1iRLc4e0-9M5om55zZps",
      "score": 4.8103976,
      "ratings": 0,
      "category": "GAME",
      "url": "https://play.google.com/store/apps/details?id=com.tg.zjxsc2.tw",
      "price": 0,
      "free": true,
      "platform": "android"
    },
    {
      "rank": 74,
      "appId": "com.sinyee.babybus.cat",
      "name": "Little Panda's Cat Game",
      "developer": "BabyBus",
      "icon": "https://play-lh.googleusercontent.com/r9viX3nM3m0enxLPSrVZ8zgoaWOIClW5BvkkxNQPB6vnpiGMZyqtUxpwAhpOQf731wM1k6tnmBusuKMD_MGcvQ",
      "score": 3.939759,
      "ratings": 0,
      "category": "GAME",
      "url": "https://play.google.com/store/apps/details?id=com.sinyee.babybus.cat",
      "price": 0,
      "free": true,
      "platform": "android"
    },
    {
      "rank": 75,
      "appId": "com.igg.android.doomsdaylastsurvivors",
      "name": "Doomsday: Last Survivors",
      "developer": "IGG.COM",
      "icon": "https://play-lh.googleusercontent.com/c-tjU8jhF6Jbm0T1UGVNIkc21IMcjLsdDy9iKU0zLvlMvUJC9EC79mgVTiRrv0J5AKM0AQ3tqsGu9y0XR5UTR-I",
      "score": 4.4674397,
      "ratings": 0,
      "category": "GAME",
      "url": "https://play.google.com/store/apps/details?id=com.igg.android.doomsdaylastsurvivors",
      "price": 0,
      "free": true,
      "platform": "android"
    },
    {
      "rank": 76,
      "appId": "com.unept.leveldevil",
      "name": "Level Devil - NOT A Troll Game",
      "developer": "Poki.com",
      "icon": "https://play-lh.googleusercontent.com/S3eBd-KYQf5Cj2Wciggw2qNtRsF3aPr3laKJl6vfY-8BX395fhp-TVtGNcU1xdP06w",
      "score": 4.16,
      "ratings": 0,
      "category": "GAME",
      "url": "https://play.google.com/store/apps/details?id=com.unept.leveldevil",
      "price": 0,
      "free": true,
      "platform": "android"
    },
    {
      "rank": 77,
      "appId": "com.igs.mjstar31",
      "name": "麻將 明星3缺1-16張Mahjong、Slot、Poker",
      "developer": "International Games System Co., Ltd.",
      "icon": "https://play-lh.googleusercontent.com/yuV4tD6NPil5Dec8tFkZ83B95KbkOdN4DZmsOhLzSbXjqd_B1Nkyde1kNQCQyYOGyJfmGLkvIsvLHdIrzNumxA",
      "score": 4.642551,
      "ratings": 0,
      "category": "GAME",
      "url": "https://play.google.com/store/apps/details?id=com.igs.mjstar31",
      "price": 0,
      "free": true,
      "platform": "android"
    },
    {
      "rank": 78,
      "appId": "com.percent.aos.cooptd",
      "name": "Coop TD: Together",
      "developer": "Supermagic",
      "icon": "https://play-lh.googleusercontent.com/yZyZYyDE0Gu7zDpa__H6Ly8zDnvj82nVvKmPKLoVpvPg8cb4VENp2Hr7WQsDuSn_RtVO",
      "score": 4.4363637,
      "ratings": 0,
      "category": "GAME",
      "url": "https://play.google.com/store/apps/details?id=com.percent.aos.cooptd",
      "price": 0,
      "free": true,
      "platform": "android"
    },
    {
      "rank": 79,
      "appId": "com.tkrush.battle.hero.slash.three.kingdoms.game",
      "name": "三國衝衝衝",
      "developer": "Mohamedae738",
      "icon": "https://play-lh.googleusercontent.com/ewRb7Vi4eMXPFbyjpcLBVREYHbO4nibEHhVvdJ80VwHbW0IW34bzWLvPnv1WzBYYObNkJF8GR0aKJYy7C52X",
      "score": 4.5945945,
      "ratings": 0,
      "category": "GAME",
      "url": "https://play.google.com/store/apps/details?id=com.tkrush.battle.hero.slash.three.kingdoms.game",
      "price": 0,
      "free": true,
      "platform": "android"
    },
    {
      "rank": 80,
      "appId": "com.samudera.romantic.screw",
      "name": "Romantic Screw Puzzle",
      "developer": "KonyilApps",
      "icon": "https://play-lh.googleusercontent.com/zaFO4SzNk_5QYTpugC61t2qZAdAM6dvo67QOit0KdQ36vCvPUOS0yuCrhC9rAnE7TAysKJbPRXI3d4nPmvH5eg",
      "score": 0,
      "ratings": 0,
      "category": "GAME",
      "url": "https://play.google.com/store/apps/details?id=com.samudera.romantic.screw",
      "price": 0,
      "free": true,
      "platform": "android"
    },
    {
      "rank": 81,
      "appId": "com.brain.crazy.joygame",
      "name": "Brain Puzzle 3: Crazy Mind",
      "developer": "JoyGame Studio",
      "icon": "https://play-lh.googleusercontent.com/YoP4Pd_zbzGWIAAU9WwRsndXXDKbeXH5vUAVRKAwHh9WwgUEx1F1u3O38F9kjXQEISgT5lpor3ZEJQ1dXM2q798",
      "score": 4.7788463,
      "ratings": 0,
      "category": "GAME",
      "url": "https://play.google.com/store/apps/details?id=com.brain.crazy.joygame",
      "price": 0,
      "free": true,
      "platform": "android"
    },
    {
      "rank": 82,
      "appId": "com.xianni.tw",
      "name": "仙逆M-官方正版授權",
      "developer": "Amazing Cat Interactive Entertainment Technology",
      "icon": "https://play-lh.googleusercontent.com/4EtLwskBNehCysbLvM_x0jRcFBsUr0RvGH7KlM_XQV-4jIBXT0nWLgIkyFhXcCFihJSVfCv2cQrG-_Qp__i77A",
      "score": 4.6399345,
      "ratings": 0,
      "category": "GAME",
      "url": "https://play.google.com/store/apps/details?id=com.xianni.tw",
      "price": 0,
      "free": true,
      "platform": "android"
    },
    {
      "rank": 83,
      "appId": "io.randomco.travel",
      "name": "Travel Town - Merge Adventure",
      "developer": "Magmatic Games LTD",
      "icon": "https://play-lh.googleusercontent.com/JUd09-Jkgctks6QibZBPeqnpPA-6A6nMXZqAW9Fa0MKOsolbvGKSXEnuq9nxiKNCFVOT",
      "score": 4.7988825,
      "ratings": 0,
      "category": "GAME",
      "url": "https://play.google.com/store/apps/details?id=io.randomco.travel",
      "price": 0,
      "free": true,
      "platform": "android"
    },
    {
      "rank": 84,
      "appId": "com.scopely.monopolygo",
      "name": "MONOPOLY GO!",
      "developer": "Scopely",
      "icon": "https://play-lh.googleusercontent.com/DfYkSl-nQoMNLX2bec7EwHemrvyDYmDgzIR1jcsyt0ZAcmO_SKjuu0a1o1iSwtnl8_g",
      "score": 4.659436,
      "ratings": 0,
      "category": "GAME",
      "url": "https://play.google.com/store/apps/details?id=com.scopely.monopolygo",
      "price": 0,
      "free": true,
      "platform": "android"
    },
    {
      "rank": 85,
      "appId": "com.goods.master3d.triple.puzzle",
      "name": "Goods Master 3D:Matching Games",
      "developer": "Cobby Labs",
      "icon": "https://play-lh.googleusercontent.com/wRdaAthNlwv_LdWAbbXUMtO3XPPopxVoZYQ5OBgoHepXehMvg2so33dNqVdouKORFmA",
      "score": 4.045045,
      "ratings": 0,
      "category": "GAME",
      "url": "https://play.google.com/store/apps/details?id=com.goods.master3d.triple.puzzle",
      "price": 0,
      "free": true,
      "platform": "android"
    },
    {
      "rank": 86,
      "appId": "com.combo.yarnflow",
      "name": "Yarn Loop",
      "developer": "Combo Game",
      "icon": "https://play-lh.googleusercontent.com/DliylMEnevS_giunP2OosFM0RxOwTCl6DLN1krnWvhCt5T90OMWeAzMtntoTK1TqOkA7vd8Xnw_mtbUlBmfDSEA",
      "score": 4.719512,
      "ratings": 0,
      "category": "GAME",
      "url": "https://play.google.com/store/apps/details?id=com.combo.yarnflow",
      "price": 0,
      "free": true,
      "platform": "android"
    },
    {
      "rank": 87,
      "appId": "com.oakever.tiletrip",
      "name": "Tile Explorer - Triple Match",
      "developer": "Oakever Games",
      "icon": "https://play-lh.googleusercontent.com/kwa0XzNS0QNIWthk_gQ5Jrzc0myF56RNXuehCN5YSMKjNeFesOnvkvXEBYi5zIAtC6aM",
      "score": 4.7896905,
      "ratings": 0,
      "category": "GAME",
      "url": "https://play.google.com/store/apps/details?id=com.oakever.tiletrip",
      "price": 0,
      "free": true,
      "platform": "android"
    },
    {
      "rank": 88,
      "appId": "com.ttx.wzdwj",
      "name": "文字大玩家",
      "developer": "KAITUOZHE NETWORK TECHNOLOGY LIMITED",
      "icon": "https://play-lh.googleusercontent.com/ZFCJYSCokoiBE6kAVpuSbOrssjHpjkEeD6xFpNSJPVPM4-cYp23L3-sSjFNQ01Ztdg",
      "score": 4.018248,
      "ratings": 0,
      "category": "GAME",
      "url": "https://play.google.com/store/apps/details?id=com.ttx.wzdwj",
      "price": 0,
      "free": true,
      "platform": "android"
    },
    {
      "rank": 89,
      "appId": "com.netmarble.gotasia",
      "name": "Game of Thrones Kingsroad",
      "developer": "Netmarble",
      "icon": "https://play-lh.googleusercontent.com/j7o9-bE6N0s71hZvO5qbYqG9V0kvbiMHsPNCjQoKD4kR0OiD5wK3NZKY2eCV1VNStH9pX8BTlxsn_5qhxC3G",
      "score": 4.2540984,
      "ratings": 0,
      "category": "GAME",
      "url": "https://play.google.com/store/apps/details?id=com.netmarble.gotasia",
      "price": 0,
      "free": true,
      "platform": "android"
    },
    {
      "rank": 90,
      "appId": "com.xhqhgame.lz",
      "name": "星海奇航：海盗來了",
      "developer": "StreamFlow Games",
      "icon": "https://play-lh.googleusercontent.com/elsotPoCshMOfu-bYB_urpUySv8peLVtENgW4zpYKDTt7orxdt5l2YnPjneBqUmLfWaOZqQ0SlYjtAsm4mNj",
      "score": 4.6938777,
      "ratings": 0,
      "category": "GAME",
      "url": "https://play.google.com/store/apps/details?id=com.xhqhgame.lz",
      "price": 0,
      "free": true,
      "platform": "android"
    },
    {
      "rank": 91,
      "appId": "com.pocket.sort.coin.puzzle.game",
      "name": "Pocket Sort: Coin Merge Puzzle",
      "developer": "SayGames Ltd",
      "icon": "https://play-lh.googleusercontent.com/Bo1AzzdXdwig0sc0hx0b0MtL2GymhF3beO3cxiW-W3PGuONQ-33gKKAT9FgUCRh8AQ",
      "score": 4.4752474,
      "ratings": 0,
      "category": "GAME",
      "url": "https://play.google.com/store/apps/details?id=com.pocket.sort.coin.puzzle.game",
      "price": 0,
      "free": true,
      "platform": "android"
    },
    {
      "rank": 92,
      "appId": "com.cliffs.pro.cell.building.crazy.clever.craft",
      "name": "Block Crazy Robo World Craft",
      "developer": "Prokids Studio",
      "icon": "https://play-lh.googleusercontent.com/K3ncdCrbnHb-Po_gNuiJldSG7lfczGR0ZdFs3zoV28yTqPnzWQh07l2xI3rgMiIPsA",
      "score": 4.3,
      "ratings": 0,
      "category": "GAME",
      "url": "https://play.google.com/store/apps/details?id=com.cliffs.pro.cell.building.crazy.clever.craft",
      "price": 0,
      "free": true,
      "platform": "android"
    },
    {
      "rank": 93,
      "appId": "com.cardsofwaifu.duel.gp",
      "name": "Cards of Waifu: Collect & Duel",
      "developer": "RBJ Elite",
      "icon": "https://play-lh.googleusercontent.com/sdvfWBlLtfcqfNFPsCiWIitHw18xZ7NrQyYr8kV0Lz2LDqGymnI1lapC5mgI-OFXf8ZUmoa58lrf3ueVzLwCIQw",
      "score": 0,
      "ratings": 0,
      "category": "GAME",
      "url": "https://play.google.com/store/apps/details?id=com.cardsofwaifu.duel.gp",
      "price": 0,
      "free": true,
      "platform": "android"
    },
    {
      "rank": 94,
      "appId": "com.puzzlegame.match.jewels.adventure",
      "name": "Jewels Adventure Match Blast",
      "developer": "Lynn Mobile Puzzle Games",
      "icon": "https://play-lh.googleusercontent.com/dCgJVqwym4obdlfDuIaQCIEqfJ7s1msYQenbRiA5gRmhlE660uNVbXZpZFPQAyBSajE",
      "score": 4.73,
      "ratings": 0,
      "category": "GAME",
      "url": "https://play.google.com/store/apps/details?id=com.puzzlegame.match.jewels.adventure",
      "price": 0,
      "free": true,
      "platform": "android"
    },
    {
      "rank": 95,
      "appId": "com.hks.brain",
      "name": "Brainstorming Master",
      "developer": "Hks Games",
      "icon": "https://play-lh.googleusercontent.com/3fE15q2sGkbDR7owHGpO3Lnrw4EM6da-9CjfBHfYJRIRCLtD2vQixHdM3LsHbeXQQLnO",
      "score": 4.586207,
      "ratings": 0,
      "category": "GAME",
      "url": "https://play.google.com/store/apps/details?id=com.hks.brain",
      "price": 0,
      "free": true,
      "platform": "android"
    },
    {
      "rank": 96,
      "appId": "com.xh.wxlh.android",
      "name": "無盡輪迴：鬼域摸金",
      "developer": "POPJOY",
      "icon": "https://play-lh.googleusercontent.com/noICce_al0HnX9F30Yz5oNr7lV7sVGSK2YrmDpga0KzHG0fG5ceHMRjwl_TcVF5i1mc",
      "score": 3.924274,
      "ratings": 0,
      "category": "GAME",
      "url": "https://play.google.com/store/apps/details?id=com.xh.wxlh.android",
      "price": 0,
      "free": true,
      "platform": "android"
    },
    {
      "rank": 97,
      "appId": "com.bunbunstudio.magicblocktiles",
      "name": "Music Piano 7: Rush Song Games",
      "developer": "Melodya Muses",
      "icon": "https://play-lh.googleusercontent.com/VfO-PCbrxFFXYI5VDd66-AOsrBdVqovRcbAB_T0VJlhMEHdMty7dYgvjXnB_tJGH8BR7WM7TREpV1wRr_Njl",
      "score": 4.5964465,
      "ratings": 0,
      "category": "GAME",
      "url": "https://play.google.com/store/apps/details?id=com.bunbunstudio.magicblocktiles",
      "price": 0,
      "free": true,
      "platform": "android"
    },
    {
      "rank": 98,
      "appId": "jp.co.goodroid.hyper.puzzle.arrows3dcubepuzzle",
      "name": "ArrowCube - 3DPuzzle",
      "developer": "GOODROID,Inc.",
      "icon": "https://play-lh.googleusercontent.com/k_9MZtpdy3gYNVgynIWwv-1omuSkl4WGr5bOKYT-PJDC5PsEdFQMXWEBU7Jr3TfyjeBviAD3DN3_2KpDhGfa",
      "score": 4.601852,
      "ratings": 0,
      "category": "GAME",
      "url": "https://play.google.com/store/apps/details?id=jp.co.goodroid.hyper.puzzle.arrows3dcubepuzzle",
      "price": 0,
      "free": true,
      "platform": "android"
    },
    {
      "rank": 99,
      "appId": "com.gear2.letsgolegends",
      "name": "Let's Go Legends!",
      "developer": "GEAR2",
      "icon": "https://play-lh.googleusercontent.com/X1vx6vKvVj-KxOodTx-gCS5SSpUdekh2BcGhUajo0B7z7ly0VAgcOoAEbqzEs3HhlgijmMChM7pUkKZOvLHWYA",
      "score": 4.457944,
      "ratings": 0,
      "category": "GAME",
      "url": "https://play.google.com/store/apps/details?id=com.gear2.letsgolegends",
      "price": 0,
      "free": true,
      "platform": "android"
    },
    {
      "rank": 100,
      "appId": "com.cedargames.mysterytown",
      "name": "Mystery Town: Merge Games",
      "developer": "Cedar Games Studio",
      "icon": "https://play-lh.googleusercontent.com/dgF-7gzJzmqOFh6BNmg48dHIaHhqtqLWqUjDic-rS2COxhfWlBCaa5_PaLsxtvZKcLA",
      "score": 4.8490567,
      "ratings": 0,
      "category": "GAME",
      "url": "https://play.google.com/store/apps/details?id=com.cedargames.mysterytown",
      "price": 0,
      "free": true,
      "platform": "android"
    }
  ]
}